ason/__init__.py
ason/ason.py
ason_text-0.0.1.dist-info/METADATA
ason_text-0.0.1.dist-info/WHEEL
ason_text-0.0.1.dist-info/top_level.txt
ason_text-0.0.1.dist-info/RECORD
