Metadata-Version: 2.4
Name: ason-text
Version: 0.0.1
Summary: Fast and clean alternative to JSON called ASON
Home-page: https://github.com/username/ason-mahir
Author: Mahir
Classifier: Programming Language :: Python :: 3
Classifier: License :: OSI Approved :: MIT License
Classifier: Operating System :: OS Independent
Requires-Python: >=3.7
Dynamic: author
Dynamic: classifier
Dynamic: description
Dynamic: description-content-type
Dynamic: home-page
Dynamic: requires-python
Dynamic: summary
